geotrigger
