Metadata-Version: 1.1
Name: geotrigger-python
Version: 0.1.1
Summary: A simple client library for interacting with the ArcGIS Geotrigger API.
Home-page: https://github.com/esri/geotrigger-python
Author: Josh Yaganeh
Author-email: jyaganeh@esri.com
License: UNKNOWN
Platform: UNKNOWN
Classifier: Development Status :: 4 - Beta
Classifier: Environment :: Console
Classifier: Environment :: Web Environment
Classifier: Intended Audience :: Developers
Classifier: License :: OSI Approved :: Apache Software License
Classifier: Operating System :: OS Independent
Classifier: Programming Language :: Python
Requires: requests
